{
    "create_account_roles": true,
    "create_operator_roles": true,
    "create_oidc": true,
    "account_role_prefix": "rosa-pub4",
    "operator_role_prefix": "rosa-pub4",
    "cluster_name": "rosa-pub-1",
    "openshift_version": "4.15.9",
    "autoscaling_enabled": true,
    "multi_az": true,
    "min_replicas": 3,
    "max_replicas": 6,
    "zones": 3,
    "machine_pools": {
      "1": {
          "name": "testpool",
          "machine_type": "r5.xlarge",
          "replicas": 3
      }
    },
    "identity_providers": {
    },
    "seed": {
      "deploy": "false"
    },
    "tags": {
        "cluster-name": "rosa-pub-1"
    }
}